[
  {
    "id": "1727229294885",
    "content": "《摄大乘论的读法》句要17：为何声闻乘教法中分别建立**四谛与十二缘起**两个教理子系统？\n\n声闻乘教理何以说四谛，又说十二缘起，放到不同**缘起关系**中考察，就一目了然，四谛是为建立**受用缘起**而说，十二缘起是为建立**业感缘起**而说。\n\n当然，四谛、十二缘起都具有普遍摄受性质，但其最初建立，是为配合不同的缘起关系的。因此，四谛先说“苦谛”，而十二缘起先说“无明”，***受用缘起以苦为本质，而业感缘起以无明为发轫***。\n\n何以声闻乘教理需要深入到业感缘起层面，因为仅仅了解欲望的产生机制，不足以对治欲望，因为***只要还有自我的观念隐藏着，就必定不断重新生成欲望***，因此必须深入到业感缘起，通过**破除自我观念**来摧毁欲望的生成机制。",
    "timestamp": "2024-09-25T01:54:54.885Z"
  },
  {
    "id": "1727086054238",
    "content": "成功人士的七个习惯\n\n![GYFhteGaMAAY9bh.jpg](https://raw.githubusercontent.com/moonopposite/tinymind-blog/main/assets/images/2024-09-23/1727086027373.jpg)",
    "timestamp": "2024-09-23T10:07:34.238Z"
  },
  {
    "id": "1727085603134",
    "content": "![GYFhpsTbMAALOUI.jpg](https://raw.githubusercontent.com/moonopposite/tinymind-blog/main/assets/images/2024-09-23/1727085501909.jpg)\n选择>努力(思维的层次)\n",
    "timestamp": "2024-09-23T10:00:03.134Z"
  }
]